horizon/__init__.py
horizon/client.py
horizon/del_ec2.py
horizon/takeoff.py
horizon/aws/__init__.py
horizon/aws/iam.py
horizon/aws/models.py
horizon/aws/titan_ec2.py
horizon/aws/titan_sagemaker.py
horizon/logs/__init__.py
horizon/logs/cloud_logs.py
horizon/scripts/pull_takeoff_image.sh
horizon/scripts/push_takeoff_ecr.sh
horizon/utils/__init__.py
horizon/utils/checks.py
horizon/utils/docker_utils.py
horizon/utils/ec2_utils.py
horizon/utils/style.py
horizon/utils/yaml_utils.py
horizon_takeoff-0.0.4.4.dist-info/LICENSE
horizon_takeoff-0.0.4.4.dist-info/METADATA
horizon_takeoff-0.0.4.4.dist-info/WHEEL
horizon_takeoff-0.0.4.4.dist-info/entry_points.txt
horizon_takeoff-0.0.4.4.dist-info/top_level.txt
horizon_takeoff-0.0.4.4.dist-info/RECORD
