Metadata-Version: 2.1
Name: horizon-takeoff
Version: 0.0.4.4
Summary: Auto-deploy the Takeoff Server on AWS for LLM inference
Home-page: UNKNOWN
Author: InquestGeronimo
Author-email: rcostanl@gmail.com
License: Apache-2.0 license
Keywords: cloud,titanml,server,LLM,NLP,MLOps,deployment
Platform: UNKNOWN
Classifier: Development Status :: 1 - Planning
Classifier: Intended Audience :: Developers
Classifier: Programming Language :: Python :: 3
Classifier: Operating System :: Unix
License-File: LICENSE
Requires-Dist: boto3 >=1.34.4
Requires-Dist: pydantic >=2.5.3
Requires-Dist: pyyaml >=6.0.1
Requires-Dist: requests >=2.31.0
Requires-Dist: rich >=12.6.0
